CAPP/AsciiArt.py
CAPP/Commands.py
CAPP/__init__.py
CAPP-0.0.dist-info/License
CAPP-0.0.dist-info/METADATA
CAPP-0.0.dist-info/WHEEL
CAPP-0.0.dist-info/entry_points.txt
CAPP-0.0.dist-info/top_level.txt
CAPP-0.0.dist-info/RECORD
