Metadata-Version: 2.1
Name: CAPP
Version: 0.0
Summary: Console Application Creator
Author: EnDaTeam
License: MIT License        
Project-URL: Homepage, https://github.com/EnDaTeam/EnDa-Console-App-Package
Keywords: console,application,terminal
Classifier: License :: OSI Approved :: MIT License
Classifier: Programming Language :: Python
Classifier: Programming Language :: Python :: 3
Requires-Python: >=3.0
License-File: License
Requires-Dist: colorama (>=0.4.6)
Requires-Dist: pystyle (>=2.0)
Requires-Dist: pyfiglet (>=0.7)
